separability/__init__.py
separability/activations.py
separability/data/imagenet_birds.json
separability/data/llama_most_common_tokens.json
separability/data_classes.py
separability/detoxify.py
separability/eval.py
separability/mia.py
separability/model.py
separability/model_maps.py
separability/model_repos.py
separability/nn.py
separability/parser.py
separability/prune.py
separability/scoring.py
separability/texts.py
separability-0.9.2.dist-info/METADATA
separability-0.9.2.dist-info/WHEEL
separability-0.9.2.dist-info/RECORD
